satella/__init__.py
satella/dao.py
satella/db.py
satella/exceptions.py
satella/files.py
satella/imports.py
satella/json.py
satella/parsing.py
satella/posix.py
satella/processes.py
satella/random.py
satella/warnings.py
satella/cassandra/__init__.py
satella/cassandra/common.py
satella/cassandra/future.py
satella/cassandra/parallel.py
satella/coding/__init__.py
satella/coding/algos.py
satella/coding/ctxt_managers.py
satella/coding/deep_compare.py
satella/coding/deleters.py
satella/coding/environment.py
satella/coding/expect_exception.py
satella/coding/fun_static.py
satella/coding/generators.py
satella/coding/iterators.py
satella/coding/metaclasses.py
satella/coding/misc.py
satella/coding/optionals.py
satella/coding/overloading.py
satella/coding/predicates.py
satella/coding/recast_exceptions.py
satella/coding/typing.py
satella/coding/concurrent/__init__.py
satella/coding/concurrent/atomic.py
satella/coding/concurrent/callablegroup.py
satella/coding/concurrent/functions.py
satella/coding/concurrent/id_allocator.py
satella/coding/concurrent/list_processor.py
satella/coding/concurrent/locked_dataset.py
satella/coding/concurrent/locked_structure.py
satella/coding/concurrent/monitor.py
satella/coding/concurrent/queue.py
satella/coding/concurrent/sync.py
satella/coding/concurrent/thread.py
satella/coding/concurrent/thread_collection.py
satella/coding/concurrent/timer.py
satella/coding/concurrent/value.py
satella/coding/concurrent/futures/__init__.py
satella/coding/concurrent/futures/call_in_future.py
satella/coding/concurrent/futures/collection.py
satella/coding/concurrent/futures/futures.py
satella/coding/concurrent/futures/wrapped_executor.py
satella/coding/decorators/__init__.py
satella/coding/decorators/arguments.py
satella/coding/decorators/decorators.py
satella/coding/decorators/flow_control.py
satella/coding/decorators/preconditions.py
satella/coding/decorators/retry_dec.py
satella/coding/resources/__init__.py
satella/coding/resources/cp_manager.py
satella-2.26.6.dist-info/LICENSE
satella-2.26.6.dist-info/METADATA
satella-2.26.6.dist-info/WHEEL
satella-2.26.6.dist-info/top_level.txt
satella-2.26.6.dist-info/RECORD
