Metadata-Version: 2.1
Name: satella
Version: 2.26.6
Summary: Utilities for writing servers in Python
Author-email: Piotr Maślanka <pmaslanka@smok.co>
License: MIT License
Project-URL: Homepage, https://git.dms-serwis.com.pl/smokserwis/satella
Project-URL: Documentation, https://smokserwis.docs.smok.co/satella
Project-URL: Issues, https://git.dms-serwis.com.pl/smokserwis/satella/-/issues
Project-URL: Repository, https://git.dms-serwis.com.pl/smokserwis/satella
Project-URL: Changelog, https://git.dms-serwis.com.pl/smokserwis/satella/-/blob/master/CHANGELOG.md?ref_type=heads
Keywords: ha,high availability,scalable,scalability,server,metrics,tracing,instrumentation
Classifier: Programming Language :: Python
Classifier: Programming Language :: Python :: 3.7
Classifier: Programming Language :: Python :: 3.8
Classifier: Programming Language :: Python :: 3.9
Classifier: Programming Language :: Python :: 3.10
Classifier: Programming Language :: Python :: 3.11
Classifier: Programming Language :: Python :: 3.12
Classifier: Programming Language :: Python :: Implementation :: CPython
Classifier: Programming Language :: Python :: Implementation :: PyPy
Classifier: Operating System :: OS Independent
Classifier: Development Status :: 5 - Production/Stable
Classifier: License :: OSI Approved :: MIT License
Classifier: Topic :: Software Development :: Libraries
Requires-Python: >=3.7
License-File: LICENSE
Requires-Dist: psutil>=5.9.8
Provides-Extra: dev
Requires-Dist: pylint; extra == "dev"
Requires-Dist: toml; extra == "dev"
Requires-Dist: requests; extra == "dev"
Requires-Dist: codeclimate-test-reporter; extra == "dev"
Requires-Dist: opentracing; extra == "dev"
Provides-Extra: extras
Requires-Dist: requests; extra == "extras"
Requires-Dist: pyyaml; extra == "extras"
Requires-Dist: toml; extra == "extras"
Requires-Dist: ujson; extra == "extras"
Requires-Dist: cassandra-driver; extra == "extras"
Requires-Dist: opentracing; extra == "extras"
Provides-Extra: test
Requires-Dist: pytest-cov; extra == "test"
Requires-Dist: pytest-xdist; extra == "test"
Requires-Dist: pytest; extra == "test"
Requires-Dist: pytest-forked; extra == "test"
Requires-Dist: pluggy; extra == "test"
Requires-Dist: py; extra == "test"
Requires-Dist: coverage; extra == "test"
